[
  {
    "_id": { "$oid": "592f072f362d3200591d51e0" },
    "heartRate": 85,
    "calories": 1442,
    "distance": 2396,
    "createdAt": "2017-05-31T18:10:55.165Z",
    "updatedAt": "2017-05-31T18:10:55.165Z"
  },
  {
    "_id": { "$oid": "592f0725362d3200591d51df" },
    "heartRate": 73,
    "calories": 1342,
    "distance": 2096,
    "createdAt": "2017-05-31T18:10:45.004Z",
    "updatedAt": "2017-05-31T18:10:45.004Z"
  },
  {
    "_id": { "$oid": "592f071a362d3200591d51de" },
    "heartRate": 83,
    "calories": 1222,
    "distance": 2026,
    "createdAt": "2017-05-31T18:10:34.363Z",
    "updatedAt": "2017-05-31T18:10:34.363Z"
  },
  {
    "_id": { "$oid": "592f070f362d3200591d51dd" },
    "heartRate": 75,
    "calories": 1122,
    "distance": 1946,
    "createdAt": "2017-05-31T18:10:23.692Z",
    "updatedAt": "2017-05-31T18:10:23.692Z"
  },
  {
    "_id": { "$oid": "592f06d8362d3200591d51db" },
    "heartRate": 77,
    "calories": 910,
    "distance": 1600,
    "createdAt": "2017-05-31T18:09:28.494Z",
    "updatedAt": "2017-05-31T18:09:28.494Z"
  },
  {
    "_id": { "$oid": "592f06cf362d3200591d51da" },
    "heartRate": 73,
    "calories": 860,
    "distance": 1411,
    "createdAt": "2017-05-31T18:09:19.661Z",
    "updatedAt": "2017-05-31T18:09:19.661Z"
  },
  {
    "_id": { "$oid": "592f06c2362d3200591d51d9" },
    "heartRate": 66,
    "calories": 820,
    "distance": 1209,
    "createdAt": "2017-05-31T18:09:06.012Z",
    "updatedAt": "2017-05-31T18:09:06.012Z"
  },
  {
    "_id": { "$oid": "592f06b1362d3200591d51d8" },
    "heartRate": 67,
    "calories": 770,
    "distance": 1090,
    "createdAt": "2017-05-31T18:08:49.393Z",
    "updatedAt": "2017-05-31T18:08:49.393Z"
  },
  {
    "_id": { "$oid": "592f067d362d3200591d51d7" },
    "heartRate": 70,
    "calories": 731,
    "distance": 1009,
    "createdAt": "2017-05-31T18:07:57.418Z",
    "updatedAt": "2017-05-31T18:07:57.418Z"
  },
  {
    "_id": { "$oid": "592f066f362d3200591d51d6" },
    "heartRate": 90,
    "calories": 631,
    "distance": 982,
    "createdAt": "2017-05-31T18:07:43.321Z",
    "updatedAt": "2017-05-31T18:07:43.321Z"
  },
  {
    "_id": { "$oid": "592f0661362d3200591d51d5" },
    "heartRate": 110,
    "calories": 529,
    "distance": 733,
    "createdAt": "2017-05-31T18:07:29.811Z",
    "updatedAt": "2017-05-31T18:07:29.811Z"
  },
  {
    "_id": { "$oid": "592f0652362d3200591d51d4" },
    "heartRate": 80,
    "calories": 400,
    "distance": 600,
    "createdAt": "2017-05-31T18:07:14.499Z",
    "updatedAt": "2017-05-31T18:07:14.499Z"
  },
  {
    "_id": { "$oid": "592f0648362d3200591d51d3" },
    "heartRate": 66,
    "calories": 160,
    "distance": 400,
    "createdAt": "2017-05-31T18:07:04.936Z",
    "updatedAt": "2017-05-31T18:07:04.936Z"
  },
  {
    "_id": { "$oid": "592f063c362d3200591d51d2" },
    "heartRate": 65,
    "calories": 100,
    "distance": 300,
    "createdAt": "2017-05-31T18:06:52.990Z",
    "updatedAt": "2017-05-31T18:06:52.990Z"
  },
  {
    "_id": { "$oid": "592f062c362d3200591d51d1" },
    "heartRate": 60,
    "calories": 0,
    "distance": 0,
    "createdAt": "2017-05-31T18:06:36.045Z",
    "updatedAt": "2017-05-31T18:06:36.045Z"
  }
]
